tq_openai_utils/__init__.py
tq_openai_utils/count_tokens.py
tq_openai_utils/funcs.py
tq_openai_utils-0.0.1.post1.dist-info/licenses/LICENSE
tq_openai_utils-0.0.1.post1.dist-info/METADATA
tq_openai_utils-0.0.1.post1.dist-info/WHEEL
tq_openai_utils-0.0.1.post1.dist-info/top_level.txt
tq_openai_utils-0.0.1.post1.dist-info/RECORD
